compositry/__init__.py
compositry/state.py
compositry/tasks.py
compositry-0.4.0.dist-info/LICENSE
compositry-0.4.0.dist-info/WHEEL
compositry-0.4.0.dist-info/METADATA
compositry-0.4.0.dist-info/RECORD
